anylearn/__about__.py
anylearn/__init__.py
anylearn/config.py
anylearn/env.py
anylearn/analyzers/__init__.py
anylearn/analyzers/artifact_collector.py
anylearn/anyboard/__init__.py
anylearn/anyboard/utils.py
anylearn/anyboard/reader/__init__.py
anylearn/anyboard/reader/base.py
anylearn/anyboard/reader/cloud_reader.py
anylearn/anyboard/reader/metric/__init__.py
anylearn/anyboard/reader/metric/base.py
anylearn/anyboard/reader/metric/histogram.py
anylearn/anyboard/reader/metric/scalar.py
anylearn/anyboard/reader/metric/utils.py
anylearn/anyboard/writer/__init__.py
anylearn/anyboard/writer/manager.py
anylearn/anyboard/writer/summary.py
anylearn/anyboard/writer/watch.py
anylearn/anyboard/writer/writers/__init__.py
anylearn/anyboard/writer/writers/base.py
anylearn/anyboard/writer/writers/csv_writer.py
anylearn/anyboard/writer/writers/iotdb_writer.py
anylearn/applications/__init__.py
anylearn/applications/algorithm_manager.py
anylearn/applications/git_progress_printer.py
anylearn/applications/quickstart.py
anylearn/applications/tracking.py
anylearn/applications/utils.py
anylearn/cli/__init__.py
anylearn/cli/_utils.py
anylearn/cli/agent.py
anylearn/cli/cli.py
anylearn/cli/jupload.py
anylearn/cli/localtrain.py
anylearn/interfaces/__init__.py
anylearn/interfaces/base.py
anylearn/interfaces/mirror.py
anylearn/interfaces/project.py
anylearn/interfaces/train_tag.py
anylearn/interfaces/train_task.py
anylearn/interfaces/user.py
anylearn/interfaces/quota/__init__.py
anylearn/interfaces/quota/group.py
anylearn/interfaces/resource/__init__.py
anylearn/interfaces/resource/algorithm.py
anylearn/interfaces/resource/dataset.py
anylearn/interfaces/resource/file.py
anylearn/interfaces/resource/model.py
anylearn/interfaces/resource/resource.py
anylearn/interfaces/resource/resource_downloader.py
anylearn/interfaces/resource/resource_uploader.py
anylearn/sdk/__init__.py
anylearn/sdk/auth.py
anylearn/sdk/client.py
anylearn/sdk/console.py
anylearn/sdk/context.py
anylearn/sdk/errors.py
anylearn-0.20.7.dist-info/licenses/LICENSE
anylearn-0.20.7.dist-info/METADATA
anylearn-0.20.7.dist-info/WHEEL
anylearn-0.20.7.dist-info/entry_points.txt
anylearn-0.20.7.dist-info/top_level.txt
anylearn-0.20.7.dist-info/RECORD
