Metadata-Version: 2.4
Name: anylearn
Version: 0.20.7
Summary: Anylearn Python SDK
Author: Dmagine
Author-email: anylearn@nelbds.org.cn
License: Proprietary
Classifier: Development Status :: 3 - Alpha
Classifier: Programming Language :: Python :: 3
Classifier: License :: Other/Proprietary License
Classifier: Operating System :: OS Independent
Classifier: Intended Audience :: Developers
Classifier: Topic :: Software Development :: Libraries
Classifier: Topic :: Software Development :: Libraries :: Python Modules
Requires-Python: >=3.7
License-File: LICENSE
Requires-Dist: cryptography~=41.0.5
Requires-Dist: GitPython
Requires-Dist: paramiko~=3.3.1
Requires-Dist: requests>=2.25.0
Requires-Dist: ruamel.yaml
Requires-Dist: tqdm
Requires-Dist: urllib3>=1.26.0
Requires-Dist: rich
Requires-Dist: typer[all]==0.11.0
Requires-Dist: numpy
Requires-Dist: apache-iotdb==1.3.2.post0
Dynamic: author
Dynamic: author-email
Dynamic: classifier
Dynamic: description
Dynamic: description-content-type
Dynamic: license
Dynamic: license-file
Dynamic: requires-dist
Dynamic: requires-python
Dynamic: summary
